datodms/__init__.py
datodms/datodms.py
datodms/test.py
datodms-0.0.3.dist-info/LICENCE.txt
datodms-0.0.3.dist-info/METADATA
datodms-0.0.3.dist-info/WHEEL
datodms-0.0.3.dist-info/top_level.txt
datodms-0.0.3.dist-info/RECORD
