Metadata-Version: 2.1
Name: datodms
Version: 0.0.3
Summary: Function to convert decimal angel to dms
Home-page: UNKNOWN
Author: nm
Author-email: UNKNOWN
License: MIT
Keywords: dms
Platform: UNKNOWN
Classifier: Development Status :: 5 - Production/Stable
Classifier: Intended Audience :: Education
Classifier: Operating System :: Microsoft :: Windows :: Windows 10
Classifier: License :: OSI Approved :: MIT License
Classifier: Programming Language :: Python :: 3
